{"b":"Hosea","c":1,"l":"h","v":[[1,[["דְּבַר\\־","de.var-","[the] word of","דָּבָר",null,1,"HNcmsc",": word"],["יְהוָ֣ה\\׀","Yah.weh","Yahweh","יהוה",null,1,"HNpt","LORD"],["אֲשֶׁ֣ר","'a.Sher","which","אֲשֶׁר",null,9,"HTr","which"],["הָיָ֗ה","ha.Yah","it came","הָיָה",null,2,"HVqp3ms","to be"],["אֶל\\־","'el-","to","אֶל",null,3,"HR","to(wards)"],["הוֹשֵׁ֙עַ֙","ho.She.a'","Hosea","הוֹשֵׁעַ",null,1,"HNpm","Hosea"],["בֶּן\\־","ben-","[the] son of","בֵּן",null,1,"HNcmsc",": child"],["בְּאֵרִ֔י","be.'e.Ri","Beeri","בְּאֵרִי",null,1,"HNpm","Beeri"],["בִּ/ימֵ֨י","bi./Mei","in [the] days of","ב",null,1,"HR/Ncmpc","in/{H3117G=יוֹם=: day"],["עֻזִּיָּ֥ה","'u.zi.Yah","Uzziah","עֻזִּיָּהוּ",null,1,"HNpm","Uzziah"],["יוֹתָ֛ם","yo.Tam","Jotham","יוֹתָם",null,1,"HNpm","Jotham"],["אָחָ֥ז","'a.Chaz","Ahaz","אָחָז",null,1,"HNpm","Ahaz"],["יְחִזְקִיָּ֖ה","ye.chiz.ki.Yah","Hezekiah","יְחִזְקִיָּה",null,1,"HNpm","Hezekiah"],["מַלְכֵ֣י","mal.Khei","[the] kings of","מֶ֫לֶךְ",null,1,"HNcmpc","king"],["יְהוּדָ֑ה","ye.hu.Dah","Judah","יְהוּדָה",null,1,"HNpl","Judah"],["וּ/בִ/ימֵ֛י","u./vi./Mei","and in [the] days of","ו",null,1,"HC/R/Ncmpc","and/H9003=ב=in/{H3117G=יוֹם=: day"],["יָרָבְעָ֥ם","ya.ra.ve.'Am","Jeroboam","יָֽרָבְעָם",null,1,"HNpm","Jeroboam"],["בֶּן\\־","ben-","[the] son of","בֵּן",null,1,"HNcmsc",": child"],["יוֹאָ֖שׁ","yo.'Ash","Joash","יוֹאָשׁ",null,1,"HNpm","Joash"],["מֶ֥לֶךְ","Me.lekh","[the] king of","מֶ֫לֶךְ",null,1,"HNcmsc","king"],["יִשְׂרָאֵֽל\\׃","Yis.ra.'El","Israel","יִשְׂרָאֵל",null,1,"HNpl","Israel"]]],[2,[["תְּחִלַּ֥ת","te.chi.Lat","[the] beginning","תְּחִלָּה",null,1,"HNcfsc","beginning"],["דִּבֶּר\\־","di.ber-","<of> [when] he spoke","דָבַר",null,2,"HVpp3ms",": speak"],["יְהוָ֖ה","Yah.weh","Yahweh","יהוה",null,1,"HNpt","LORD"],["בְּ/הוֹשֵׁ֑עַ\\ \\פ","be./ho.She.a'","by Hosea","ב",null,1,"HR/Npm","in/{H1954J=הוֹשֵׁעַ=Hosea"],["וַ/יֹּ֨אמֶר","va/i.Yo.mer","and he said","ו",null,2,"Hc/Vqw3ms","&/{H0559=אָמַר=to say"],["יְהוָ֜ה","Yah.weh","Yahweh","יהוה",null,1,"HNpt","LORD"],["אֶל\\־","'el-","to","אֶל",null,3,"HR","to(wards)"],["הוֹשֵׁ֗עַ","ho.She.a'","Hosea","הוֹשֵׁעַ",null,1,"HNpm","Hosea"],["לֵ֣ךְ","lekh","go","הָלַךְ",null,2,"HVqv2ms",": went"],["קַח\\־","kach-","take","לָקַח",null,2,"HVqv2ms",": marry"],["לְ/ךָ֞","le./Kha","for yourself","ל",null,3,"HR/Sp2ms","to/{H9031=Os2m=you"],["אֵ֤שֶׁת","'E.shet","a wife of","אִשָּׁה",null,1,"HNcfsc",": wife"],["זְנוּנִים֙","ze.nu.Nim","prostitution<s>","זְנוּנִים",null,1,"HNcmpa","fornication"],["וְ/יַלְדֵ֣י","ve./yal.Dei","and children of","ו",null,1,"HC/Ncmpc","and/{H3206=יֶ֫לֶד=youth"],["זְנוּנִ֔ים","ze.nu.Nim","prostitution<s>","זְנוּנִים",null,1,"HNcmpa","fornication"],["כִּֽי\\־","ki-","for","כִּי",null,9,"HTc","for"],["זָנֹ֤ה","za.Noh","continually <prostitute itself>","זָנָה",null,2,"HVqaa","to fornicate"],["תִזְנֶה֙","tiz.Neh","it prostitutes itself","זָנָה",null,2,"HVqi3fs","to fornicate"],["הָ/אָ֔רֶץ","ha./'A.retz","the land","ה",null,1,"HTd/Ncfsa","the/{H0776G=אֶ֫רֶץ=: country;_planet"],["מֵֽ/אַחֲרֵ֖י","me./'a.cha.Rei","from after","מ",null,3,"HR/Acmpc","from/{H0310A=אַחַר=after"],["יְהוָֽה\\׃","Yah.weh","Yahweh","יהוה",null,1,"HNpt","LORD"]]],[3,[["וַ/יֵּ֙לֶךְ֙","va/i.Ye.lekh","and he went","ו",null,2,"Hc/Vqw3ms","&/{H1980G=הָלַךְ=: went"],["וַ/יִּקַּ֔ח","va/i.yi.Kach","and he took","ו",null,2,"Hc/Vqw3ms","&/{H3947I=לָקַח=: marry"],["אֶת\\־","'et-","<obj.>","אֵת",null,9,"HTo","[Obj.]"],["גֹּ֖מֶר","Go.mer","Gomer","גֹּ֫מֶר",null,1,"HNpf","Gomer"],["בַּת\\־","bat-","[the] daughter of","בַּת",null,1,"HNcfsc",": daughter"],["דִּבְלָ֑יִם","div.La.yim","Diblaim","דִּבְלַ֫יִם",null,1,"HNpm","Diblaim"],["וַ/תַּ֥הַר","va./Ta.har","and she conceived","ו",null,2,"Hc/Vqw3fs","&/{H2029=הָרָה=to conceive"],["וַ/תֵּֽלֶד\\־","va./te.led-","and she bore","ו",null,2,"Hc/Vqw3fs","&/{H3205=יָלַד=to beget"],["ל֖/וֹ","l/o","to him","ל",null,3,"HR/Sp3ms","to/{H9033=Os3m=him"],["בֵּֽן\\׃","Ben","a son","בֵּן",null,1,"HNcmsa",": child"]]],[4,[["וַ/יֹּ֤אמֶר","va/i.Yo.mer","and he said","ו",null,2,"Hc/Vqw3ms","&/{H0559=אָמַר=to say"],["יְהוָה֙","Yah.weh","Yahweh","יהוה",null,1,"HNpt","LORD"],["אֵלָ֔י/ו","'e.La/v","to him","אֶל",null,3,"HR/Sp3ms","to(wards)"],["קְרָ֥א","ke.Ra'","call","קָרָא",null,2,"HVqv2ms",": call_by"],["שְׁמ֖/וֹ","she.M/o","name his","שֵׁם",null,1,"HNcmsc/Sp3ms","name"],["יִזְרְעֶ֑אל","yiz.re.'El","Jezreel","יִזְרְעֶאל",null,1,"HNpm","Jezreel"],["כִּי\\־","ki-","for","כִּי",null,9,"HTc","for"],["ע֣וֹד","od","yet","עוֹד",null,6,"HAcmsa","still"],["מְעַ֗ט","me.'At","a little","מְעַט",null,1,"HNcmsa","little"],["וּ/פָ֨קַדְתִּ֜י","u./Fa.kad.Ti","and I will visit","ו",null,2,"Hc/Vqq1cs","&/{H6485H=פָּקַד=: punish"],["אֶת\\־","'et-","<obj.>","אֵת",null,9,"HTo","[Obj.]"],["דְּמֵ֤י","de.Mei","[the] blood<s> of","דָּם",null,1,"HNcmpc","blood"],["יִזְרְעֶאל֙","yiz.re.'eL","Jezreel","יִזְרְעֶאל",null,1,"HNpl","Jezreel"],["עַל\\־","'al-","on","עַל",null,3,"HR","upon"],["בֵּ֣ית","beit","[the] house of","בַּ֫יִת",null,1,"HNcmsc",": home"],["יֵה֔וּא","ye.Hu'","Jehu","יֵהוּא",null,1,"HNpm","Jehu"],["וְ/הִ֨שְׁבַּתִּ֔י","ve./Hish.ba.Ti","and I will put an end to","ו",null,4,"Hc/Vhq1cs","&/{H7673A=שָׁבַת=to cease"],["מַמְלְכ֖וּת","mam.le.Khut","[the] kingdom of","מַמְלָכוּת",null,1,"HNcfsc","kingdom"],["בֵּ֥ית","beit","[the] house of","בַּ֫יִת",null,1,"HNcmsc",": home"],["יִשְׂרָאֵֽל\\׃","Yis.ra.'El","Israel","יִשְׂרָאֵל",null,1,"HNpl","Israel"]]],[5,[["וְ/הָיָ֖ה","ve./ha.Yah","and it will be","ו",null,2,"Hc/Vqq3ms","&/{H1961=הָיָה=to be"],["בַּ/יּ֣וֹם","ba/i.Yom","on the day","ב",null,1,"HRd/Ncmsa","in/{H3117G=יוֹם=: day"],["הַ/ה֑וּא","ha./Hu'","<the> that","ה",null,9,"HTd/Pp3ms","the/{H1931=הוּא=he;_she;_it"],["וְ/שָֽׁבַרְתִּי֙","ve./sha.var.Ti","and I will break","ו",null,2,"Hc/Vqq1cs","&/{H7665=שָׁבַר=to break"],["אֶת\\־","'et-","<obj.>","אֵת",null,9,"HTo","[Obj.]"],["קֶ֣שֶׁת","Ke.shet","[the] bow of","קֶ֫שֶׁת",null,1,"HNcfsc","bow"],["יִשְׂרָאֵ֔ל","Yis.ra.'El","Israel","יִשְׂרָאֵל",null,1,"HNpl","Israel"],["בְּ/עֵ֖מֶק","be./'E.mek","in [the] valley of","ב",null,1,"HR/Ncmsc","in/{H6010M=עֵ֫מֶק=valley"],["יִזְרְעֶֽאל\\׃","yiz.re.'El","Jezreel","יִזְרְעֶאל",null,1,"HNpl","of Jezreel"]]],[6,[["וַ/תַּ֤הַר","va./Ta.har","and she conceived","ו",null,2,"Hc/Vqw3fs","&/{H2029=הָרָה=to conceive"],["עוֹד֙","'Od","again","עוֹד",null,6,"HAcmsa","still"],["וַ/תֵּ֣לֶד","va./Te.led","and she bore","ו",null,2,"Hc/Vqw3fs","&/{H3205=יָלַד=to beget"],["בַּ֔ת","Bat","a daughter","בַּת",null,1,"HNcfsa",": daughter"],["וַ/יֹּ֣אמֶר","va/i.Yo.mer","and he said","ו",null,2,"Hc/Vqw3ms","&/{H0559=אָמַר=to say"],["ל֔/וֹ","l/o","to him","ל",null,3,"HR/Sp3ms","to/{H9033=Os3m=him"],["קְרָ֥א","ke.Ra'","call","קָרָא",null,2,"HVqv2ms",": call_by"],["שְׁמָ֖/הּ","she.Ma/h","name her","שֵׁם",null,1,"HNcmsc/Sp3fs","name"],["לֹ֣א","lo'","Lo-","לֹא רֻחָ֫מָה",null,1,"HNpf","No Mercy"],["רֻחָ֑מָה","ru.Cha.mah","Ruhamah","לֹא רֻחָ֫מָה",null,1,"HNpf","No Mercy"],["כִּי֩","ki","for","כִּי",null,9,"HTc","for"],["לֹ֨א","lo'","not","לֹא",null,9,"HTn","not"],["אוֹסִ֜יף","'o.Sif","I will repeat","יָסַף",null,2,"HVhi1cs",": again"],["ע֗וֹד","od","again","עוֹד",null,6,"HAcmsa","still"],["אֲרַחֵם֙","'a.ra.Chem","I will have compassion on","רָחַם",null,2,"HVpi1cs","to have compassion"],["אֶת\\־","'et-","<obj.>","אֵת",null,9,"HTo","[Obj.]"],["בֵּ֣ית","beit","[the] house of","בַּ֫יִת",null,1,"HNcmsc",": home"],["יִשְׂרָאֵ֔ל","Yis.ra.'El","Israel","יִשְׂרָאֵל",null,1,"HNpl","Israel"],["כִּֽי\\־","ki-","that","כִּי",null,9,"HTc","for"],["נָשֹׂ֥א","na.So'","certainly <forgive>","נָשָׂא",null,2,"HVqaa",": forgive"],["אֶשָּׂ֖א","'e.Sa'","I will forgive","נָשָׂא",null,2,"HVqi1cs",": forgive"],["לָ/הֶֽם\\׃","la./Hem","<to> them","ל",null,3,"HR/Sp3mp","to/{H9038=Op3m=them"]]],[7,[["וְ/אֶת\\־","ve./'Et","and <obj.>","ו",null,4,"HC/To","and/{H0853=אֵת=[Obj.]"],["בֵּ֤ית","beit","[the] house of","בַּ֫יִת",null,1,"HNcmsc",": home"],["יְהוּדָה֙","ye.hu.Dah","Judah","יְהוּדָה",null,1,"HNpl","Judah"],["אֲרַחֵ֔ם","'a.ra.Chem","I will have compassion on","רָחַם",null,2,"HVpi1cs","to have compassion"],["וְ/הֽוֹשַׁעְתִּ֖י/ם","ve./ho.sha'.Ti/m","and I will save them","ו",null,4,"Hc/Vhq1cs/Sp3mp","&/{H3467=יָשַׁע=to save"],["בַּ/יהוָ֣ה","ba./Yah.weh","by Yahweh","ב",null,1,"HR/Npt","in/{H3068G=יהוה=LORD"],["אֱלֹֽהֵי/הֶ֑ם","'e.lo.hei./Hem","God their","אֱלֹהִים",null,1,"HNcmpc/Sp3mp","God"],["וְ/לֹ֣א","ve./Lo'","and not","ו",null,4,"HC/Tn","and/{H3808=לֹא=not"],["אֽוֹשִׁיעֵ֗/ם","'o.shi.'E/m","I will save them","יָשַׁע",null,2,"HVhi1cs/Sp3mp","to save"],["בְּ/קֶ֤שֶׁת","be./Ke.shet","by bow","ב",null,1,"HR/Ncfsa","in/{H7198=קֶ֫שֶׁת=bow"],["וּ/בְ/חֶ֙רֶב֙","u./ve./Che.rev","and by sword","ו",null,1,"HC/R/Ncfsa","and/H9003=ב=in/{H2719=חֶ֫רֶב=sword"],["וּ/בְ/מִלְחָמָ֔ה","u./ve./mil.cha.Mah","and by battle","ו",null,1,"HC/R/Ncfsa","and/H9003=ב=in/{H4421=מִלְחָמָה=battle"],["בְּ/סוּסִ֖ים","be./su.Sim","by horses","ב",null,1,"HR/Ncmpa","in/{H5483M=סוּס=horse"],["וּ/בְ/פָרָשִֽׁים\\׃","u./ve./fa.ra.Shim","and by horsemen","ו",null,1,"HC/R/Ncmpa","and/H9003=ב=in/{H6571B=פָּרָשׁ=horseman"]]],[8,[["וַ/תִּגְמֹ֖ל","va./tig.Mol","and she weaned","ו",null,2,"Hc/Vqw3fs","&/{H1580=גָּמַל=to wean"],["אֶת\\־","'et-","<obj.>","אֵת",null,9,"HTo","[Obj.]"],["לֹ֣א","lo'","Lo-","לֹא רֻחָ֫מָה",null,1,"HNpf","No Mercy"],["רֻחָ֑מָה","ru.Cha.mah","Ruhamah","לֹא רֻחָ֫מָה",null,1,"HNpf","No Mercy"],["וַ/תַּ֖הַר","va./Ta.har","and she conceived","ו",null,2,"Hc/Vqw3fs","&/{H2029=הָרָה=to conceive"],["וַ/תֵּ֥לֶד","va./Te.led","and she bore","ו",null,2,"Hc/Vqw3fs","&/{H3205=יָלַד=to beget"],["בֵּֽן\\׃","Ben","a son","בֵּן",null,1,"HNcmsa",": child"]]],[9,[["וַ/יֹּ֕אמֶר","va/i.Yo.mer","and he said","ו",null,2,"Hc/Vqw3ms","&/{H0559=אָמַר=to say"],["קְרָ֥א","ke.Ra'","call","קָרָא",null,2,"HVqv2ms",": call_by"],["שְׁמ֖/וֹ","she.M/o","name his","שֵׁם",null,1,"HNcmsc/Sp3ms","name"],["לֹ֣א","lo'","Lo-","לֹא עַמִּי",null,1,"HNpm","Not My People"],["עַמִּ֑י","'a.Mi","Ammi","לֹא עַמִּי",null,1,"HNpm","Not My People"],["כִּ֤י","ki","for","כִּי",null,9,"HTc","for"],["אַתֶּם֙","'a.Tem","you","אַתֶּם",null,8,"HPp2mp","you(m.p.)"],["לֹ֣א","lo'","not","לֹא",null,9,"HTn","not"],["עַמִּ֔/י","'a.M/i","[are] people my","עַם",null,1,"HNcmsc/Sp1bs",": people"],["וְ/אָנֹכִ֖י","ve./'a.no.Khi","and I","ו",null,4,"HC/Pp1bs","and/{H0595=אָֽנֹכִ֫י=I"],["לֹֽא\\־","lo'-","not","לֹא",null,9,"HTn","not"],["אֶהְיֶ֥ה","'eh.Yeh","I will belong","הָיָה",null,2,"HVqi1cs","to be"],["לָ/כֶֽם\\׃\\ \\ס","la./Khem","to you","ל",null,3,"HR/Sp2mp","to/{H9036=Op2m=you"]]]]}